obelixtools/__init__.py
obelixtools/__main__.py
obelixtools-1.1.1.dist-info/LICENSE
obelixtools-1.1.1.dist-info/METADATA
obelixtools-1.1.1.dist-info/WHEEL
obelixtools-1.1.1.dist-info/top_level.txt
obelixtools-1.1.1.dist-info/RECORD
