Metadata-Version: 2.1
Name: obelixtools
Version: 1.1.1
Summary: Useful tools I need in many projects.
Home-page: https://github.com/loelkes/pypi-obelixtools
Author: Christian Lölkes
Author-email: christian.loelkes@gmail.com
License: UNKNOWN
Platform: UNKNOWN
Classifier: Programming Language :: Python :: 3
Classifier: Programming Language :: Python :: 2.7
Classifier: License :: OSI Approved :: MIT License
Classifier: Operating System :: OS Independent
Requires-Python: >=2.7
Requires-Dist: requests
Requires-Dist: requests[security]
Requires-Dist: sseclient
